chiabip158.cpython-313-darwin.so
chiabip158-1.5.4.dist-info/RECORD
chiabip158-1.5.4.dist-info/WHEEL
chiabip158-1.5.4.dist-info/top_level.txt
chiabip158-1.5.4.dist-info/METADATA
chiabip158-1.5.4.dist-info/licenses/LICENSE
