Metadata-Version: 2.4
Name: chiabip158
Version: 1.5.4
Summary: Chia BIP158 (wraps C++)
Home-page: https://github.com/Chia-Network/chiabip158
Author: Mariano Sorgente
Author-email: mariano@chia.net
License: Apache License
Requires-Python: >=3.7
License-File: LICENSE
Dynamic: author
Dynamic: author-email
Dynamic: description
Dynamic: description-content-type
Dynamic: home-page
Dynamic: license
Dynamic: license-file
Dynamic: requires-python
Dynamic: summary
